sample/__init__.py
sample/main.py
gopipsample-0.1.0.dist-info/METADATA
gopipsample-0.1.0.dist-info/WHEEL
gopipsample-0.1.0.dist-info/top_level.txt
gopipsample-0.1.0.dist-info/RECORD
